photon_weave/__init__.py
photon_weave/_math/__init__.py
photon_weave/_math/ops.py
photon_weave/constants/__init__.py
photon_weave/extra/__init__.py
photon_weave/extra/einsum_constructor.py
photon_weave/extra/expression_interpreter.py
photon_weave/operation/__init__.py
photon_weave/operation/composite_operation.py
photon_weave/operation/custom_state_operation.py
photon_weave/operation/fock_operation.py
photon_weave/operation/helpers/__init__.py
photon_weave/operation/helpers/fock_dimension_esitmation.py
photon_weave/operation/operation.py
photon_weave/operation/polarization_operation.py
photon_weave/photon_weave.py
photon_weave/state/__init__.py
photon_weave/state/base_state.py
photon_weave/state/composite_envelope.py
photon_weave/state/custom_state.py
photon_weave/state/envelope.py
photon_weave/state/exceptions.py
photon_weave/state/expansion_levels.py
photon_weave/state/fock.py
photon_weave/state/polarization.py
photon_weave/state/utils/__init__.py
photon_weave/state/utils/measurements.py
photon_weave/state/utils/operations.py
photon_weave/state/utils/representation.py
photon_weave/state/utils/routing.py
photon_weave/state/utils/state_transform.py
photon_weave/state/utils/trace_out.py
photon_weave-0.1.8.dist-info/LICENSE
photon_weave-0.1.8.dist-info/METADATA
photon_weave-0.1.8.dist-info/WHEEL
photon_weave-0.1.8.dist-info/RECORD
