Metadata-Version: 2.3
Name: photon_weave
Version: 0.1.8
Summary: A quantum optics simulator for modeling and analysis of quantum systems.
License: Apache-2.0
Keywords: quantum optics,simulation,quantum mechanics
Author: Simon Sekavčnik, Kareem H. El-Safty, Janis Nötzel
Requires-Python: >=3.10
Classifier: License :: OSI Approved :: Apache Software License
Classifier: Operating System :: OS Independent
Classifier: Programming Language :: Python :: 3
Classifier: Programming Language :: Python :: 3.10
Classifier: Programming Language :: Python :: 3.11
Classifier: Programming Language :: Python :: 3.12
Classifier: Programming Language :: Python :: 3.13
Classifier: Topic :: Scientific/Engineering :: Physics
Requires-Dist: jax (==0.5.0)
Requires-Dist: jaxlib (==0.5.0)
Project-URL: Homepage, https://github.com/tqsd/photon_weave
Project-URL: Repository, https://github.com/tqsd/photon_weave
